hollybooks/__init__.py
hollybooks/bible.py
hollybooks/quran.py
hollybooks/torah.py
holybooks/__init__.py
holybooks/bible.py
holybooks/quran.py
holybooks/torah.py
holybooks-0.1.2.dist-info/LICENCE.txt
holybooks-0.1.2.dist-info/METADATA
holybooks-0.1.2.dist-info/WHEEL
holybooks-0.1.2.dist-info/top_level.txt
holybooks-0.1.2.dist-info/RECORD
