Metadata-Version: 2.1
Name: holybooks
Version: 0.1.2
Summary: An Api Wrapper for extracting info from: quran api and bible api. I didn't made the document for this so for now read the file in my github(https://github.com/TheGenocides/holybooks) to find all functions there. I will add more holybooks in the future!
Home-page: UNKNOWN
Author: TheGenocide
Author-email: luke.genesis.hyder@gmail.com
License: MIT
Keywords: holybooks,holybook,scripture,kitab,quran,bible,torah
Platform: UNKNOWN
Classifier: Development Status :: 5 - Production/Stable
Classifier: Intended Audience :: Education
Classifier: Operating System :: Microsoft :: Windows :: Windows 10
Classifier: License :: OSI Approved :: MIT License
Classifier: Programming Language :: Python :: 3
Requires-Dist: requests
Requires-Dist: aiohttp
